file_convertion_tools/__init__.py
file_convertion_tools/audio.py
file_convertion_tools/cleanup.py
file_convertion_tools/concatenate_files.py
file_convertion_tools/count_pdf_pages.py
file_convertion_tools/csv_to_md.py
file_convertion_tools/json_to_yaml.py
file_convertion_tools/load_toml.py
file_convertion_tools/make_md_table.py
file_convertion_tools/movie.py
file_convertion_tools/pdf_to_csv_tabula.py
file_convertion_tools/pdf_to_txt.py
file_convertion_tools/seven_zip_utils.py
file_convertion_tools/sort_yaml.py
file_convertion_tools/txt_to_csv.py
file_convertion_tools-0.0.16.dist-info/LICENSE
file_convertion_tools-0.0.16.dist-info/METADATA
file_convertion_tools-0.0.16.dist-info/WHEEL
file_convertion_tools-0.0.16.dist-info/RECORD
