Metadata-Version: 2.1
Name: file-convertion-tools
Version: 0.0.16
Summary: common file conversions
Author: Gustav Rasmussen
Requires-Python: >=3.11,<4.0
Classifier: Programming Language :: Python :: 3
Classifier: Programming Language :: Python :: 3.11
Classifier: Programming Language :: Python :: 3.12
Classifier: Programming Language :: Python :: 3.13
Requires-Dist: moviepy (>=1.0.3,<2.0.0)
Requires-Dist: pandas (>=2.2.3,<3.0.0)
Requires-Dist: py7zr (>=0.22.0,<0.23.0)
Requires-Dist: pypdf (>=5.1.0,<6.0.0)
Requires-Dist: pytest (>=8.3.3,<9.0.0)
Requires-Dist: pytest-cov (>=6.0.0,<7.0.0)
Requires-Dist: pyyaml (>=6.0.2,<7.0.0)
Requires-Dist: tabula-py (>=2.10.0,<3.0.0)
Requires-Dist: tabulate (>=0.9.0,<0.10.0)
